<?xml version="1.0" encoding="UTF-8"?>

<!-- generated on 2023-12-11 11:01:43 by Eclipse SUMO GUI Version 1.18.0
<configuration xmlns:xsi="http://www.w3.org/2001/XMLSchema-instance" xsi:noNamespaceSchemaLocation="http://sumo.dlr.de/xsd/sumoConfiguration.xsd">

    <input>
        <net-file value="../road_network.net.xml"/>
        <route-files value="../road_network_map.rou.xml"/>
        <additional-files value="../road_network_additional.add.xml"/>
    </input>

    <output>
        <tripinfo-output value="tripinfo.xml"/>
    </output>

    <traci_server>
        <remote-port value="51328"/>
    </traci_server>

</configuration>
-->

<detector xmlns:xsi="http://www.w3.org/2001/XMLSchema-instance" xsi:noNamespaceSchemaLocation="http://sumo.dlr.de/xsd/det_e2_file.xsd">
   <interval begin="0.00" end="40.00" id="E4_1" sampledSeconds="0.00" nVehEntered="0" nVehLeft="0" nVehSeen="0" meanSpeed="-1.00" meanTimeLoss="-1.00" meanOccupancy="0.00" maxOccupancy="0.00" meanMaxJamLengthInVehicles="0.00" meanMaxJamLengthInMeters="0.00" maxJamLengthInVehicles="0" maxJamLengthInMeters="0.00" jamLengthInVehiclesSum="0" jamLengthInMetersSum="0.00" meanHaltingDuration="0.00" maxHaltingDuration="0.00" haltingDurationSum="0.00" meanIntervalHaltingDuration="0.00" maxIntervalHaltingDuration="0.00" intervalHaltingDurationSum="0.00" startedHalts="0.00" meanVehicleNumber="0.00" maxVehicleNumber="0" />
   <interval begin="40.00" end="80.00" id="E4_1" sampledSeconds="5.18" nVehEntered="1" nVehLeft="1" nVehSeen="1" meanSpeed="16.41" meanTimeLoss="2.59" meanOccupancy="0.65" maxOccupancy="6.25" meanMaxJamLengthInVehicles="0.00" meanMaxJamLengthInMeters="0.00" maxJamLengthInVehicles="0" maxJamLengthInMeters="0.00" jamLengthInVehiclesSum="0" jamLengthInMetersSum="0.00" meanHaltingDuration="0.00" maxHaltingDuration="0.00" haltingDurationSum="0.00" meanIntervalHaltingDuration="0.00" maxIntervalHaltingDuration="0.00" intervalHaltingDurationSum="0.00" startedHalts="0.00" meanVehicleNumber="0.15" maxVehicleNumber="1" />
   <interval begin="80.00" end="120.00" id="E4_1" sampledSeconds="38.37" nVehEntered="3" nVehLeft="3" nVehSeen="3" meanSpeed="5.31" meanTimeLoss="10.34" meanOccupancy="5.37" maxOccupancy="12.50" meanMaxJamLengthInVehicles="0.50" meanMaxJamLengthInMeters="2.64" maxJamLengthInVehicles="2" maxJamLengthInMeters="11.42" jamLengthInVehiclesSum="20" jamLengthInMetersSum="105.66" meanHaltingDuration="11.00" maxHaltingDuration="12.00" haltingDurationSum="22.00" meanIntervalHaltingDuration="11.00" maxIntervalHaltingDuration="12.00" intervalHaltingDurationSum="22.00" startedHalts="2.00" meanVehicleNumber="1.02" maxVehicleNumber="2" />
   <interval begin="120.00" end="160.00" id="E4_1" sampledSeconds="0.00" nVehEntered="0" nVehLeft="0" nVehSeen="0" meanSpeed="-1.00" meanTimeLoss="-1.00" meanOccupancy="0.00" maxOccupancy="0.00" meanMaxJamLengthInVehicles="0.00" meanMaxJamLengthInMeters="0.00" maxJamLengthInVehicles="0" maxJamLengthInMeters="0.00" jamLengthInVehiclesSum="0" jamLengthInMetersSum="0.00" meanHaltingDuration="0.00" maxHaltingDuration="0.00" haltingDurationSum="0.00" meanIntervalHaltingDuration="0.00" maxIntervalHaltingDuration="0.00" intervalHaltingDurationSum="0.00" startedHalts="0.00" meanVehicleNumber="0.00" maxVehicleNumber="0" />
   <interval begin="160.00" end="200.00" id="E4_1" sampledSeconds="33.52" nVehEntered="2" nVehLeft="1" nVehSeen="2" meanSpeed="4.28" meanTimeLoss="14.16" meanOccupancy="4.38" maxOccupancy="12.50" meanMaxJamLengthInVehicles="0.55" meanMaxJamLengthInMeters="2.15" maxJamLengthInVehicles="1" maxJamLengthInMeters="3.90" jamLengthInVehiclesSum="22" jamLengthInMetersSum="85.85" meanHaltingDuration="23.00" maxHaltingDuration="23.00" haltingDurationSum="23.00" meanIntervalHaltingDuration="23.00" maxIntervalHaltingDuration="23.00" intervalHaltingDurationSum="23.00" startedHalts="1.00" meanVehicleNumber="0.88" maxVehicleNumber="2" />
   <interval begin="200.00" end="240.00" id="E4_1" sampledSeconds="2.81" nVehEntered="0" nVehLeft="1" nVehSeen="1" meanSpeed="1.39" meanTimeLoss="2.67" meanOccupancy="0.21" maxOccupancy="4.88" meanMaxJamLengthInVehicles="0.05" meanMaxJamLengthInMeters="0.16" maxJamLengthInVehicles="1" maxJamLengthInMeters="3.90" jamLengthInVehiclesSum="2" jamLengthInMetersSum="6.59" meanHaltingDuration="25.00" maxHaltingDuration="25.00" haltingDurationSum="25.00" meanIntervalHaltingDuration="2.00" maxIntervalHaltingDuration="2.00" intervalHaltingDurationSum="2.00" startedHalts="0.00" meanVehicleNumber="0.07" maxVehicleNumber="1" />
   <interval begin="240.00" end="280.00" id="E4_1" sampledSeconds="1.95" nVehEntered="1" nVehLeft="1" nVehSeen="1" meanSpeed="20.96" meanTimeLoss="0.64" meanOccupancy="0.16" maxOccupancy="6.25" meanMaxJamLengthInVehicles="0.00" meanMaxJamLengthInMeters="0.00" maxJamLengthInVehicles="0" maxJamLengthInMeters="0.00" jamLengthInVehiclesSum="0" jamLengthInMetersSum="0.00" meanHaltingDuration="0.00" maxHaltingDuration="0.00" haltingDurationSum="0.00" meanIntervalHaltingDuration="0.00" maxIntervalHaltingDuration="0.00" intervalHaltingDurationSum="0.00" startedHalts="0.00" meanVehicleNumber="0.05" maxVehicleNumber="1" />
   <interval begin="280.00" end="320.00" id="E4_1" sampledSeconds="9.22" nVehEntered="5" nVehLeft="3" nVehSeen="5" meanSpeed="20.20" meanTimeLoss="0.69" meanOccupancy="1.31" maxOccupancy="11.91" meanMaxJamLengthInVehicles="0.00" meanMaxJamLengthInMeters="0.00" maxJamLengthInVehicles="0" maxJamLengthInMeters="0.00" jamLengthInVehiclesSum="0" jamLengthInMetersSum="0.00" meanHaltingDuration="0.00" maxHaltingDuration="0.00" haltingDurationSum="0.00" meanIntervalHaltingDuration="0.00" maxIntervalHaltingDuration="0.00" intervalHaltingDurationSum="0.00" startedHalts="0.00" meanVehicleNumber="0.30" maxVehicleNumber="2" />
   <interval begin="320.00" end="360.00" id="E4_1" sampledSeconds="5.75" nVehEntered="0" nVehLeft="2" nVehSeen="2" meanSpeed="20.61" meanTimeLoss="0.67" meanOccupancy="0.73" maxOccupancy="12.50" meanMaxJamLengthInVehicles="0.00" meanMaxJamLengthInMeters="0.00" maxJamLengthInVehicles="0" maxJamLengthInMeters="0.00" jamLengthInVehiclesSum="0" jamLengthInMetersSum="0.00" meanHaltingDuration="0.00" maxHaltingDuration="0.00" haltingDurationSum="0.00" meanIntervalHaltingDuration="0.00" maxIntervalHaltingDuration="0.00" intervalHaltingDurationSum="0.00" startedHalts="0.00" meanVehicleNumber="0.17" maxVehicleNumber="2" />
   <interval begin="360.00" end="400.00" id="E4_1" sampledSeconds="43.86" nVehEntered="4" nVehLeft="1" nVehSeen="4" meanSpeed="4.91" meanTimeLoss="9.25" meanOccupancy="6.26" maxOccupancy="17.38" meanMaxJamLengthInVehicles="0.68" meanMaxJamLengthInMeters="3.63" maxJamLengthInVehicles="2" maxJamLengthInMeters="11.74" jamLengthInVehiclesSum="27" jamLengthInMetersSum="145.35" meanHaltingDuration="14.50" maxHaltingDuration="17.00" haltingDurationSum="29.00" meanIntervalHaltingDuration="14.50" maxIntervalHaltingDuration="17.00" intervalHaltingDurationSum="29.00" startedHalts="2.00" meanVehicleNumber="1.12" maxVehicleNumber="3" />
   <interval begin="400.00" end="440.00" id="E4_1" sampledSeconds="17.09" nVehEntered="0" nVehLeft="3" nVehSeen="3" meanSpeed="4.91" meanTimeLoss="4.74" meanOccupancy="2.11" maxOccupancy="17.38" meanMaxJamLengthInVehicles="0.12" meanMaxJamLengthInMeters="0.70" maxJamLengthInVehicles="2" maxJamLengthInMeters="11.40" jamLengthInVehiclesSum="5" jamLengthInMetersSum="27.81" meanHaltingDuration="17.00" maxHaltingDuration="19.00" haltingDurationSum="34.00" meanIntervalHaltingDuration="2.50" maxIntervalHaltingDuration="3.00" intervalHaltingDurationSum="5.00" startedHalts="0.00" meanVehicleNumber="0.47" maxVehicleNumber="3" />
   <interval begin="440.00" end="480.00" id="E4_1" sampledSeconds="2.00" nVehEntered="1" nVehLeft="0" nVehSeen="1" meanSpeed="21.82" meanTimeLoss="0.52" meanOccupancy="0.31" maxOccupancy="6.25" meanMaxJamLengthInVehicles="0.00" meanMaxJamLengthInMeters="0.00" maxJamLengthInVehicles="0" maxJamLengthInMeters="0.00" jamLengthInVehiclesSum="0" jamLengthInMetersSum="0.00" meanHaltingDuration="0.00" maxHaltingDuration="0.00" haltingDurationSum="0.00" meanIntervalHaltingDuration="0.00" maxIntervalHaltingDuration="0.00" intervalHaltingDurationSum="0.00" startedHalts="0.00" meanVehicleNumber="0.05" maxVehicleNumber="1" />
   <interval begin="480.00" end="520.00" id="E4_1" sampledSeconds="64.29" nVehEntered="6" nVehLeft="7" nVehSeen="7" meanSpeed="5.64" meanTimeLoss="7.58" meanOccupancy="9.04" maxOccupancy="23.63" meanMaxJamLengthInVehicles="0.40" meanMaxJamLengthInMeters="2.24" maxJamLengthInVehicles="2" maxJamLengthInMeters="11.70" jamLengthInVehiclesSum="16" jamLengthInMetersSum="89.46" meanHaltingDuration="6.33" maxHaltingDuration="9.00" haltingDurationSum="19.00" meanIntervalHaltingDuration="6.33" maxIntervalHaltingDuration="9.00" intervalHaltingDurationSum="19.00" startedHalts="3.00" meanVehicleNumber="1.75" maxVehicleNumber="4" />
   <interval begin="520.00" end="560.00" id="E4_1" sampledSeconds="0.00" nVehEntered="0" nVehLeft="0" nVehSeen="0" meanSpeed="-1.00" meanTimeLoss="-1.00" meanOccupancy="0.00" maxOccupancy="0.00" meanMaxJamLengthInVehicles="0.00" meanMaxJamLengthInMeters="0.00" maxJamLengthInVehicles="0" maxJamLengthInMeters="0.00" jamLengthInVehiclesSum="0" jamLengthInMetersSum="0.00" meanHaltingDuration="0.00" maxHaltingDuration="0.00" haltingDurationSum="0.00" meanIntervalHaltingDuration="0.00" maxIntervalHaltingDuration="0.00" intervalHaltingDurationSum="0.00" startedHalts="0.00" meanVehicleNumber="0.00" maxVehicleNumber="0" />
   <interval begin="560.00" end="600.00" id="E4_1" sampledSeconds="56.18" nVehEntered="5" nVehLeft="1" nVehSeen="5" meanSpeed="5.04" meanTimeLoss="9.33" meanOccupancy="8.39" maxOccupancy="23.72" meanMaxJamLengthInVehicles="0.70" meanMaxJamLengthInMeters="4.36" maxJamLengthInVehicles="4" maxJamLengthInMeters="26.46" jamLengthInVehiclesSum="28" jamLengthInMetersSum="174.28" meanHaltingDuration="8.00" maxHaltingDuration="11.00" haltingDurationSum="32.00" meanIntervalHaltingDuration="8.00" maxIntervalHaltingDuration="11.00" intervalHaltingDurationSum="32.00" startedHalts="4.00" meanVehicleNumber="1.45" maxVehicleNumber="4" />
   <interval begin="600.00" end="640.00" id="E4_1" sampledSeconds="29.90" nVehEntered="1" nVehLeft="5" nVehSeen="5" meanSpeed="4.87" meanTimeLoss="5.02" meanOccupancy="4.02" maxOccupancy="23.63" meanMaxJamLengthInVehicles="0.35" meanMaxJamLengthInMeters="2.30" maxJamLengthInVehicles="4" maxJamLengthInMeters="26.41" jamLengthInVehiclesSum="14" jamLengthInMetersSum="91.89" meanHaltingDuration="11.50" maxHaltingDuration="13.00" haltingDurationSum="46.00" meanIntervalHaltingDuration="3.50" maxIntervalHaltingDuration="5.00" intervalHaltingDurationSum="14.00" startedHalts="0.00" meanVehicleNumber="0.80" maxVehicleNumber="4" />
   <interval begin="640.00" end="680.00" id="E4_1" sampledSeconds="6.67" nVehEntered="2" nVehLeft="0" nVehSeen="2" meanSpeed="19.32" meanTimeLoss="1.16" meanOccupancy="1.25" maxOccupancy="12.50" meanMaxJamLengthInVehicles="0.00" meanMaxJamLengthInMeters="0.00" maxJamLengthInVehicles="0" maxJamLengthInMeters="0.00" jamLengthInVehiclesSum="0" jamLengthInMetersSum="0.00" meanHaltingDuration="0.00" maxHaltingDuration="0.00" haltingDurationSum="0.00" meanIntervalHaltingDuration="0.00" maxIntervalHaltingDuration="0.00" intervalHaltingDurationSum="0.00" startedHalts="0.00" meanVehicleNumber="0.20" maxVehicleNumber="2" />
   <interval begin="680.00" end="720.00" id="E4_1" sampledSeconds="69.27" nVehEntered="4" nVehLeft="5" nVehSeen="6" meanSpeed="3.47" meanTimeLoss="10.12" meanOccupancy="9.66" maxOccupancy="17.38" meanMaxJamLengthInVehicles="0.97" meanMaxJamLengthInMeters="5.44" maxJamLengthInVehicles="2" maxJamLengthInMeters="11.96" jamLengthInVehiclesSum="39" jamLengthInMetersSum="217.53" meanHaltingDuration="14.00" maxHaltingDuration="18.00" haltingDurationSum="42.00" meanIntervalHaltingDuration="14.00" maxIntervalHaltingDuration="18.00" intervalHaltingDurationSum="42.00" startedHalts="3.00" meanVehicleNumber="1.80" maxVehicleNumber="3" />
   <interval begin="720.00" end="760.00" id="E4_1" sampledSeconds="1.01" nVehEntered="0" nVehLeft="1" nVehSeen="1" meanSpeed="26.92" meanTimeLoss="0.09" meanOccupancy="0.01" maxOccupancy="0.39" meanMaxJamLengthInVehicles="0.00" meanMaxJamLengthInMeters="0.00" maxJamLengthInVehicles="0" maxJamLengthInMeters="0.00" jamLengthInVehiclesSum="0" jamLengthInMetersSum="0.00" meanHaltingDuration="0.00" maxHaltingDuration="0.00" haltingDurationSum="0.00" meanIntervalHaltingDuration="0.00" maxIntervalHaltingDuration="0.00" intervalHaltingDurationSum="0.00" startedHalts="0.00" meanVehicleNumber="0.05" maxVehicleNumber="1" />
   <interval begin="760.00" end="800.00" id="E4_1" sampledSeconds="7.07" nVehEntered="2" nVehLeft="2" nVehSeen="2" meanSpeed="17.92" meanTimeLoss="1.49" meanOccupancy="0.81" maxOccupancy="6.25" meanMaxJamLengthInVehicles="0.00" meanMaxJamLengthInMeters="0.00" maxJamLengthInVehicles="0" maxJamLengthInMeters="0.00" jamLengthInVehiclesSum="0" jamLengthInMetersSum="0.00" meanHaltingDuration="0.00" maxHaltingDuration="0.00" haltingDurationSum="0.00" meanIntervalHaltingDuration="0.00" maxIntervalHaltingDuration="0.00" intervalHaltingDurationSum="0.00" startedHalts="0.00" meanVehicleNumber="0.20" maxVehicleNumber="1" />
   <interval begin="800.00" end="840.00" id="E4_1" sampledSeconds="0.00" nVehEntered="0" nVehLeft="0" nVehSeen="0" meanSpeed="-1.00" meanTimeLoss="-1.00" meanOccupancy="0.00" maxOccupancy="0.00" meanMaxJamLengthInVehicles="0.00" meanMaxJamLengthInMeters="0.00" maxJamLengthInVehicles="0" maxJamLengthInMeters="0.00" jamLengthInVehiclesSum="0" jamLengthInMetersSum="0.00" meanHaltingDuration="0.00" maxHaltingDuration="0.00" haltingDurationSum="0.00" meanIntervalHaltingDuration="0.00" maxIntervalHaltingDuration="0.00" intervalHaltingDurationSum="0.00" startedHalts="0.00" meanVehicleNumber="0.00" maxVehicleNumber="0" />
   <interval begin="840.00" end="880.00" id="E4_1" sampledSeconds="0.00" nVehEntered="0" nVehLeft="0" nVehSeen="0" meanSpeed="-1.00" meanTimeLoss="-1.00" meanOccupancy="0.00" maxOccupancy="0.00" meanMaxJamLengthInVehicles="0.00" meanMaxJamLengthInMeters="0.00" maxJamLengthInVehicles="0" maxJamLengthInMeters="0.00" jamLengthInVehiclesSum="0" jamLengthInMetersSum="0.00" meanHaltingDuration="0.00" maxHaltingDuration="0.00" haltingDurationSum="0.00" meanIntervalHaltingDuration="0.00" maxIntervalHaltingDuration="0.00" intervalHaltingDurationSum="0.00" startedHalts="0.00" meanVehicleNumber="0.00" maxVehicleNumber="0" />
   <interval begin="880.00" end="920.00" id="E4_1" sampledSeconds="8.83" nVehEntered="3" nVehLeft="3" nVehSeen="3" meanSpeed="22.50" meanTimeLoss="0.76" meanOccupancy="1.23" maxOccupancy="6.25" meanMaxJamLengthInVehicles="0.00" meanMaxJamLengthInMeters="0.00" maxJamLengthInVehicles="0" maxJamLengthInMeters="0.00" jamLengthInVehiclesSum="0" jamLengthInMetersSum="0.00" meanHaltingDuration="0.00" maxHaltingDuration="0.00" haltingDurationSum="0.00" meanIntervalHaltingDuration="0.00" maxIntervalHaltingDuration="0.00" intervalHaltingDurationSum="0.00" startedHalts="0.00" meanVehicleNumber="0.28" maxVehicleNumber="1" />
   <interval begin="920.00" end="960.00" id="E4_1" sampledSeconds="0.00" nVehEntered="0" nVehLeft="0" nVehSeen="0" meanSpeed="-1.00" meanTimeLoss="-1.00" meanOccupancy="0.00" maxOccupancy="0.00" meanMaxJamLengthInVehicles="0.00" meanMaxJamLengthInMeters="0.00" maxJamLengthInVehicles="0" maxJamLengthInMeters="0.00" jamLengthInVehiclesSum="0" jamLengthInMetersSum="0.00" meanHaltingDuration="0.00" maxHaltingDuration="0.00" haltingDurationSum="0.00" meanIntervalHaltingDuration="0.00" maxIntervalHaltingDuration="0.00" intervalHaltingDurationSum="0.00" startedHalts="0.00" meanVehicleNumber="0.00" maxVehicleNumber="0" />
   <interval begin="960.00" end="1000.00" id="E4_1" sampledSeconds="100.92" nVehEntered="6" nVehLeft="2" nVehSeen="6" meanSpeed="3.99" meanTimeLoss="14.60" meanOccupancy="15.30" maxOccupancy="29.88" meanMaxJamLengthInVehicles="1.57" meanMaxJamLengthInMeters="9.75" maxJamLengthInVehicles="4" maxJamLengthInMeters="26.41" jamLengthInVehiclesSum="63" jamLengthInMetersSum="390.19" meanHaltingDuration="16.75" maxHaltingDuration="24.00" haltingDurationSum="67.00" meanIntervalHaltingDuration="16.75" maxIntervalHaltingDuration="24.00" intervalHaltingDurationSum="67.00" startedHalts="5.00" meanVehicleNumber="2.58" maxVehicleNumber="5" />
   <interval begin="1000.00" end="1001.00" id="E4_1" sampledSeconds="4.00" nVehEntered="0" nVehLeft="0" nVehSeen="4" meanSpeed="0.00" meanTimeLoss="1.00" meanOccupancy="23.63" maxOccupancy="23.63" meanMaxJamLengthInVehicles="4.00" meanMaxJamLengthInMeters="26.41" maxJamLengthInVehicles="4" maxJamLengthInMeters="26.41" jamLengthInVehiclesSum="4" jamLengthInMetersSum="26.41" meanHaltingDuration="17.75" maxHaltingDuration="25.00" haltingDurationSum="71.00" meanIntervalHaltingDuration="1.00" maxIntervalHaltingDuration="1.00" intervalHaltingDurationSum="4.00" startedHalts="0.00" meanVehicleNumber="4.00" maxVehicleNumber="4" />
</detector>
